{
  "responses": [
    {
      "labelAnnotations": [
        {
          "mid": "/m/01mw2x",
          "description": "Health Care",
          "score": 0.75218993,
          "topicality": 0.009878306
        },
        {
          "mid": "/m/02xht4g",
          "description": "Medical",
          "score": 0.7414033,
          "topicality": 0.0013153332
        },
        {
          "mid": "/m/01xgg_",
          "description": "Medical equipment",
          "score": 0.63955975,
          "topicality": 0.00014265056
        },
        {
          "mid": "/m/04sh3",
          "description": "Medicine",
          "score": 0.56814164,
          "topicality": 0.09474804
        },
        {
          "mid": "/m/018l35",
          "description": "Pharmaceutical drug",
          "score": 0.55529726,
          "topicality": 0.16587617
        }
      ]
    }
  ]
}