{
  "responses": [
    {
      "labelAnnotations": [
        {
          "mid": "/m/02yfx",
          "description": "Fluid",
          "score": 0.9555179,
          "topicality": 0.004870131
        },
        {
          "mid": "/m/04k94",
          "description": "Liquid",
          "score": 0.92011005,
          "topicality": 0.02434614
        },
        {
          "mid": "/m/01mw2x",
          "description": "Health Care",
          "score": 0.8825475,
          "topicality": 0.050089605
        },
        {
          "mid": "/m/01xgg_",
          "description": "Medical equipment",
          "score": 0.86737907,
          "topicality": 0.00013132012
        },
        {
          "mid": "/m/02xht4g",
          "description": "Medical",
          "score": 0.8453701,
          "topicality": 0.0014855426
        },
        {
          "mid": "/m/018l35",
          "description": "Pharmaceutical drug",
          "score": 0.8200039,
          "topicality": 0.20028628
        },
        {
          "mid": "/m/04sh3",
          "description": "Medicine",
          "score": 0.8185849,
          "topicality": 0.18838961
        },
        {
          "mid": "/m/01_7r6",
          "description": "Prescription drug",
          "score": 0.7914789,
          "topicality": 0.06052111
        },
        {
          "mid": "/m/02w3_ws",
          "description": "Personal care",
          "score": 0.66751605,
          "topicality": 0.00012595022
        },
        {
          "mid": "/m/04dr76w",
          "description": "Bottle",
          "score": 0.6504376,
          "topicality": 0.022310209
        },
        {
          "mid": "/m/023j4r",
          "description": "Nail",
          "score": 0.613188,
          "topicality": 0.00018420348
        },
        {
          "mid": "/m/06mq7",
          "description": "Science",
          "score": 0.5892641,
          "topicality": 0.06840771
        },
        {
          "mid": "/m/073l3",
          "description": "Solution",
          "score": 0.5741888,
          "topicality": 0.047926836
        },
        {
          "mid": "/m/03_5sv",
          "description": "Laboratory equipment",
          "score": 0.53481674,
          "topicality": 7.002773e-05
        },
        {
          "mid": "/m/01rfps",
          "description": "Pharmacy",
          "score": 0.5041446,
          "topicality": 0.02855845
        }
      ]
    }
  ]
}