{
  "responses": [
    {
      "labelAnnotations": [
        {
          "mid": "/m/083jv",
          "description": "White",
          "score": 0.9731356,
          "topicality": 0.0007504712
        },
        {
          "mid": "/m/07s6nbt",
          "description": "Text",
          "score": 0.9618123,
          "topicality": 0.011268679
        },
        {
          "mid": "/m/03gq5hm",
          "description": "Font",
          "score": 0.91200155,
          "topicality": 0.00019618319
        },
        {
          "mid": "/m/01zbnw",
          "description": "Screenshot",
          "score": 0.6232406,
          "topicality": 0.046647824
        }
      ]
    }
  ]
}