{
  "responses": [
    {
      "labelAnnotations": [
        {
          "mid": "/m/02xht4g",
          "description": "Medical",
          "score": 0.71462256,
          "topicality": 0.0011595113
        },
        {
          "mid": "/m/0hpnr",
          "description": "Hospital",
          "score": 0.6644483,
          "topicality": 0.30882818
        },
        {
          "mid": "/m/01mw2x",
          "description": "Health Care",
          "score": 0.6287385,
          "topicality": 0.06398832
        },
        {
          "mid": "/m/026w9v9",
          "description": "Medical procedure",
          "score": 0.61271185,
          "topicality": 0.014082231
        },
        {
          "mid": "/m/028hfb",
          "description": "Patient",
          "score": 0.6047338,
          "topicality": 0.19486846
        },
        {
          "mid": "/m/0174n1",
          "description": "Glove",
          "score": 0.5489223,
          "topicality": 0.0022584146
        },
        {
          "mid": "/m/0846kq",
          "description": "Scrubs",
          "score": 0.51401263,
          "topicality": 0.004309948
        }
      ]
    }
  ]
}