{
  "responses": [
    {
      "labelAnnotations": [
        {
          "mid": "/m/0hcr",
          "description": "Animation",
          "score": 0.8887378,
          "topicality": 0.021252433
        },
        {
          "mid": "/m/0215n",
          "description": "Cartoon",
          "score": 0.8650549,
          "topicality": 0.0044185473
        },
        {
          "mid": "/m/02h7lkt",
          "description": "Fictional character",
          "score": 0.84749556,
          "topicality": 0.0017538022
        },
        {
          "mid": "/m/0jxy",
          "description": "Anime",
          "score": 0.8268409,
          "topicality": 0.18337572
        },
        {
          "mid": "/m/095bb",
          "description": "Animated cartoon",
          "score": 0.8001063,
          "topicality": 0.013369399
        },
        {
          "mid": "/m/02tx1k",
          "description": "CG artwork",
          "score": 0.75298077,
          "topicality": 0.0018794745
        },
        {
          "mid": "/m/02xlf",
          "description": "Fiction",
          "score": 0.5929582,
          "topicality": 0.0007623257
        }
      ]
    }
  ]
}