{
  "responses": [
    {
      "labelAnnotations": [
        {
          "mid": "/m/03q69",
          "description": "Hair",
          "score": 0.9915328,
          "topicality": 0.045489963
        },
        {
          "mid": "/m/06pj2k",
          "description": "Lips",
          "score": 0.9847923,
          "topicality": 0.009041939
        },
        {
          "mid": "/m/06z04",
          "description": "Skin",
          "score": 0.9806759,
          "topicality": 0.008754286
        },
        {
          "mid": "/m/01ssh5",
          "description": "Shoulder",
          "score": 0.9715454,
          "topicality": 0.0225722
        },
        {
          "mid": "/m/01f43",
          "description": "Beauty",
          "score": 0.9709422,
          "topicality": 0.071103096
        },
        {
          "mid": "/m/0ds4x",
          "description": "Hairstyle",
          "score": 0.97044617,
          "topicality": 0.079772554
        },
        {
          "mid": "/m/0fc1fy",
          "description": "Black hair",
          "score": 0.9662068,
          "topicality": 0.07728366
        },
        {
          "mid": "/m/0dzd8",
          "description": "Neck",
          "score": 0.9567203,
          "topicality": 0.016961638
        },
        {
          "mid": "/m/032tl",
          "description": "Fashion",
          "score": 0.95046926
        },
        {
          "mid": "/m/091410",
          "description": "Collar",
          "score": 0.9249683,
          "topicality": 0.018833522
        },
        {
          "mid": "/m/0d1pc",
          "description": "Model",
          "score": 0.89768213,
          "topicality": 0.1463463
        },
        {
          "mid": "/m/02pd__z",
          "description": "Long hair",
          "score": 0.8957091,
          "topicality": 0.020917563
        },
        {
          "mid": "/m/02hqr87",
          "description": "Fashion Model",
          "score": 0.89244837,
          "topicality": 0.13165699
        },
        {
          "mid": "/m/01fklc",
          "description": "Pink",
          "score": 0.86976045,
          "topicality": 0.019436061
        },
        {
          "mid": "/m/031974",
          "description": "Waist",
          "score": 0.85146344,
          "topicality": 0.018495658
        },
        {
          "mid": "/m/02qbl1m",
          "description": "Photo shoot",
          "score": 0.81448406,
          "topicality": 0.04006067
        },
        {
          "mid": "/m/02ksmb",
          "description": "Brown hair",
          "score": 0.80014706,
          "topicality": 0.0036209698
        },
        {
          "mid": "/m/0dzdr",
          "description": "Thorax",
          "score": 0.7972415,
          "topicality": 0.09538944
        },
        {
          "mid": "/m/03wm22",
          "description": "Gravure idol",
          "score": 0.72784144,
          "topicality": 0.063030526
        },
        {
          "mid": "/m/09spj9",
          "description": "Layered hair",
          "score": 0.7202327,
          "topicality": 0.008478367
        },
        {
          "mid": "/m/031vtq",
          "description": "Torso",
          "score": 0.7137107,
          "topicality": 0.0005434673
        },
        {
          "mid": "/m/08y7p8",
          "description": "Abdomen",
          "score": 0.71012694,
          "topicality": 0.0012172421
        },
        {
          "mid": "/m/03sr43",
          "description": "Japanese idol",
          "score": 0.7054285,
          "topicality": 0.041237254
        },
        {
          "mid": "/m/026mhtg",
          "description": "Step cutting",
          "score": 0.63678914,
          "topicality": 0.00016839047
        },
        {
          "mid": "/m/02vxn",
          "description": "Film",
          "score": 0.6113573,
          "topicality": 0.009744837
        },
        {
          "mid": "/m/0chml9",
          "description": "Portrait photography",
          "score": 0.6062825,
          "topicality": 0.0033681376
        },
        {
          "mid": "/m/02qp_b",
          "description": "Makeover",
          "score": 0.5939244,
          "topicality": 0.00029902987
        },
        {
          "mid": "/m/0mhy4",
          "description": "Throat",
          "score": 0.5923936,
          "topicality": 0.0016152617
        },
        {
          "mid": "/m/01dv4h",
          "description": "Portrait",
          "score": 0.59193367,
          "topicality": 0.004110124
        },
        {
          "mid": "/m/027qw1p",
          "description": "Feathered hair",
          "score": 0.57221586,
          "topicality": 7.191236e-05
        },
        {
          "mid": "/m/06n0gv",
          "description": "Art Model",
          "score": 0.5395176,
          "topicality": 0.0040285788
        },
        {
          "mid": "/m/07hsg5",
          "description": "Hair care",
          "score": 0.53428394,
          "topicality": 0.00064329273
        },
        {
          "mid": "/m/01s_bn",
          "description": "Button",
          "score": 0.5093566,
          "topicality": 0.0025607685
        },
        {
          "mid": "/m/0gjxqj",
          "description": "Bangs",
          "score": 0.5046778,
          "topicality": 0.023470234
        },
        {
          "mid": "/m/053ydw",
          "description": "Crop top",
          "score": 0.5024324,
          "topicality": 0.040040296
        }
      ]
    }
  ]
}