{
  "responses": [
    {
      "labelAnnotations": [
        {
          "mid": "/m/0k65p",
          "description": "Hand",
          "score": 0.9694025,
          "topicality": 0.010285222
        },
        {
          "mid": "/m/0fsbk0",
          "description": "Health Professional",
          "score": 0.86316216,
          "topicality": 0.1694129
        },
        {
          "mid": "/m/01mw2x",
          "description": "Health Care",
          "score": 0.8161237,
          "topicality": 0.04634147
        },
        {
          "mid": "/m/02xht4g",
          "description": "Medical",
          "score": 0.8111992,
          "topicality": 0.0014335777
        },
        {
          "mid": "/m/0174n1",
          "description": "Glove",
          "score": 0.81113553,
          "topicality": 0.0033877573
        },
        {
          "mid": "/m/026w9v9",
          "description": "Medical procedure",
          "score": 0.7396152,
          "topicality": 0.013618279
        },
        {
          "mid": "/m/05t4q",
          "description": "Physician",
          "score": 0.7273766,
          "topicality": 0.14907229
        },
        {
          "mid": "/m/06yrfc",
          "description": "Medical assistant",
          "score": 0.71093625,
          "topicality": 0.011066343
        },
        {
          "mid": "/m/0fczf",
          "description": "Nurse",
          "score": 0.68938017,
          "topicality": 0.025119921
        },
        {
          "mid": "/m/0hpnr",
          "description": "Hospital",
          "score": 0.686857,
          "topicality": 0.05790799
        },
        {
          "mid": "/m/023j4r",
          "description": "Nail",
          "score": 0.67673415,
          "topicality": 0.0007362263
        },
        {
          "mid": "/m/01xgg_",
          "description": "Medical equipment",
          "score": 0.65971345,
          "topicality": 0.0002874369
        },
        {
          "mid": "/m/03fk5c",
          "description": "Clinic",
          "score": 0.6505039,
          "topicality": 0.03235231
        },
        {
          "mid": "/m/03yx9r",
          "description": "Medical glove",
          "score": 0.6385196,
          "topicality": 0.017951459
        },
        {
          "mid": "/m/02y_93f",
          "description": "Surgeon",
          "score": 0.5746157,
          "topicality": 0.028936014
        },
        {
          "mid": "/m/0846kq",
          "description": "Scrubs",
          "score": 0.5492301,
          "topicality": 0.0013074382
        },
        {
          "mid": "/m/0hgr9by",
          "description": "Safety Glove",
          "score": 0.5406809,
          "topicality": 1.4638195e-05
        },
        {
          "mid": "/m/028hfb",
          "description": "Patient",
          "score": 0.54002243,
          "topicality": 0.11399818
        },
        {
          "mid": "/m/06mq7",
          "description": "Science",
          "score": 0.5087115,
          "topicality": 0.009161617
        }
      ]
    }
  ]
}